{"msg": "", "code": "0", "data": {"attrList": [[{"attrName": "\u54c1\u724c", "attrNameId": 5150, "attrVal": "\u7d20\u6d01", "goodsId": "2c9257a15d94319f015db113203a0622", "id": 5187}, {"attrName": "\u8d27\u53f7", "attrNameId": 5151, "attrVal": "DZ1704X2-9", "goodsId": "2c9257a15d94319f015db113203a0622", "id": 5188}]], "brandName": "\u7d20\u6d01", "businessId": "4028800457b6cf7a0157b7998c39001d", "businessName": "\u5e7f\u5dde\u7d20\u6d01\u670d\u9970\u516c\u53f8", "code": "DZ1704X2-9", "detailInfo": "<p><img src=\"http://localhost:5000/images/201708051426345474699.jpg\" title=\"201708051426345474699.jpg\"/></p><p><img src=\"http://localhost:5000/images/201708051426346106478.jpg\" title=\"201708051426346106478.jpg\"/></p><p><img src=\"http://localhost:5000/images/201708051426346032077.jpg\" title=\"201708051426346032077.jpg\"/></p><p><img src=\"http://localhost:5000/images/201708051426346459934.jpg\" title=\"201708051426346459934.jpg\"/></p><p><img src=\"http://localhost:5000/images/201708051426349324442.jpg\" title=\"201708051426349324442.jpg\"/></p><p><img src=\"http://localhost:5000/images/201708051426366139052.jpg\" title=\"201708051426366139052.jpg\"/></p><p><img src=\"http://localhost:5000/images/201708051426373288665.jpg\" title=\"201708051426373288665.jpg\"/></p><p><img src=\"http://localhost:5000/images/201708051426370666072.jpg\" title=\"201708051426370666072.jpg\"/></p><p><img src=\"http://localhost:5000/images/201708051426393316381.jpg\" title=\"201708051426393316381.jpg\"/></p><p><br/></p>", "evaluateCount": 0, "freeShipNum": 5, "freight": 0, "goodsSkuId": "2c9257a15d94319f015db11320560628", "goodsSkuList": [{"goodsCode": "DZ1704X2-9", "goodsId": "2c9257a15d94319f015db113203a0622", "id": "2c9257a15d94319f015db11320560628", "price": 69, "saleCount": 0, "skuNameIds": "[316,317]", "skuNames": "[\"\u5c3a\u7801\",\"\u989c\u8272\"]", "skuValIds": "[791,795]", "skuVals": "[\"S\",\"\u9ed1\u8272\"]", "stockNum": 500, "stockNumWarn": 0}, {"goodsCode": "DZ1704X2-9", "goodsId": "2c9257a15d94319f015db113203a0622", "id": "2c9257a15d94319f015db11320580629", "price": 69, "saleCount": 0, "skuNameIds": "[316,317]", "skuNames": "[\"\u5c3a\u7801\",\"\u989c\u8272\"]", "skuValIds": "[791,796]", "skuVals": "[\"S\",\"\u84dd\u8272\"]", "stockNum": 500, "stockNumWarn": 0}, {"goodsCode": "DZ1704X2-9", "goodsId": "2c9257a15d94319f015db113203a0622", "id": "2c9257a15d94319f015db1132059062a", "price": 69, "saleCount": 0, "skuNameIds": "[316,317]", "skuNames": "[\"\u5c3a\u7801\",\"\u989c\u8272\"]", "skuValIds": "[792,795]", "skuVals": "[\"M\",\"\u9ed1\u8272\"]", "stockNum": 500, "stockNumWarn": 0}, {"goodsCode": "DZ1704X2-9", "goodsId": "2c9257a15d94319f015db113203a0622", "id": "2c9257a15d94319f015db113205b062b", "price": 69, "saleCount": 0, "skuNameIds": "[316,317]", "skuNames": "[\"\u5c3a\u7801\",\"\u989c\u8272\"]", "skuValIds": "[792,796]", "skuVals": "[\"M\",\"\u84dd\u8272\"]", "stockNum": 500, "stockNumWarn": 0}, {"goodsCode": "DZ1704X2-9", "goodsId": "2c9257a15d94319f015db113203a0622", "id": "2c9257a15d94319f015db113205d062c", "price": 69, "saleCount": 0, "skuNameIds": "[316,317]", "skuNames": "[\"\u5c3a\u7801\",\"\u989c\u8272\"]", "skuValIds": "[793,795]", "skuVals": "[\"L\",\"\u9ed1\u8272\"]", "stockNum": 500, "stockNumWarn": 0}, {"goodsCode": "DZ1704X2-9", "goodsId": "2c9257a15d94319f015db113203a0622", "id": "2c9257a15d94319f015db113205e062d", "price": 69, "saleCount": 0, "skuNameIds": "[316,317]", "skuNames": "[\"\u5c3a\u7801\",\"\u989c\u8272\"]", "skuValIds": "[793,796]", "skuVals": "[\"L\",\"\u84dd\u8272\"]", "stockNum": 500, "stockNumWarn": 0}, {"goodsCode": "DZ1704X2-9", "goodsId": "2c9257a15d94319f015db113203a0622", "id": "2c9257a15d94319f015db1132060062e", "price": 69, "saleCount": 0, "skuNameIds": "[316,317]", "skuNames": "[\"\u5c3a\u7801\",\"\u989c\u8272\"]", "skuValIds": "[794,795]", "skuVals": "[\"XL\",\"\u9ed1\u8272\"]", "stockNum": 500, "stockNumWarn": 0}, {"goodsCode": "DZ1704X2-9", "goodsId": "2c9257a15d94319f015db113203a0622", "id": "2c9257a15d94319f015db1132062062f", "price": 69, "saleCount": 0, "skuNameIds": "[316,317]", "skuNames": "[\"\u5c3a\u7801\",\"\u989c\u8272\"]", "skuValIds": "[794,796]", "skuVals": "[\"XL\",\"\u84dd\u8272\"]", "stockNum": 500, "stockNumWarn": 0}], "goodsSkuNameList": [{"skuName": "\u5c3a\u7801", "skuValList": [{"current": true, "skuVal": "S", "skuNameId": 316, "skuValId": 791}, {"current": false, "skuVal": "M", "skuNameId": 316, "skuValId": 792}, {"current": false, "skuVal": "L", "skuNameId": 316, "skuValId": 793}, {"current": false, "skuVal": "XL", "skuNameId": 316, "skuValId": 794}], "skuNameId": 316}, {"skuName": "\u989c\u8272", "skuValList": [{"current": true, "skuVal": "\u9ed1\u8272", "skuNameId": 317, "skuValId": 795}, {"current": false, "skuVal": "\u84dd\u8272", "skuNameId": 317, "skuValId": 796}], "skuNameId": 317}], "goodsSkuValIds": [791, 795], "goodsSkuVals": ["S", "\u9ed1\u8272"], "id": "2c9257a15d94319f015db113203a0622", "logo": "http://localhost:5000/images/201708051425137413023.jpg", "marketPrice": 169, "minBuyNum": 200, "name": "2017\u5e74\u590f\u5b63\u65b0\u6b3e\u4f11\u95f2\u88e4\u5973\u957f\u88e4\u5587\u53ed\u88e4", "photoList": [{"goodsId": "2c9257a15d94319f015db113203a0622", "id": "2c9257a15e3c46cf015e425cb2d00a72", "photo": "http://localhost:5000/images/201708051425137413023.jpg", "thumPhoto": "http://localhost:5000/images/201708051425137413023_thumbnail.jpg"}, {"goodsId": "2c9257a15d94319f015db113203a0622", "id": "2c9257a15e3c46cf015e425cb2d10a73", "photo": "http://localhost:5000/images/201708051425163354261.jpg", "thumPhoto": "http://localhost:5000/images/201708051425163354261_thumbnail.jpg"}, {"goodsId": "2c9257a15d94319f015db113203a0622", "id": "2c9257a15e3c46cf015e425cb2d30a74", "photo": "http://localhost:5000/images/201708051425185310189.jpg", "thumPhoto": "http://localhost:5000/images/201708051425185310189_thumbnail.jpg"}, {"goodsId": "2c9257a15d94319f015db113203a0622", "id": "2c9257a15e3c46cf015e425cb2d50a75", "photo": "http://localhost:5000/images/201708051425206937905.jpg", "thumPhoto": "http://localhost:5000/images/201708051425206937905_thumbnail.jpg"}, {"goodsId": "2c9257a15d94319f015db113203a0622", "id": "2c9257a15e3c46cf015e425cb2d60a76", "photo": "http://localhost:5000/images/201708051425223254228.jpg", "thumPhoto": "http://localhost:5000/images/201708051425223254228_thumbnail.jpg"}], "price": 69, "saleCount": 0, "shareAmount": null, "shareTimes": null, "shareTips": null, "sourceFlag": 1, "startTime": "2017-08-05 14:26:46", "status": 1, "stockNum": 500, "thumLogo": "http://localhost:5000/images/201708051425137413023_thumbnail.jpg", "validEndTime": "2017-09-15 14:24:50", "wholeNum": 0, "wholePrice": null}, "validDate": 0}