{"msg": "", "code": "0", "data": {"attrList": [[{"attrName": "\u54c1\u724c", "attrNameId": 20726, "attrVal": "\u7d20\u6d01", "goodsId": "2c9257a15dea5b37015dee11ccac001c", "id": 20763}, {"attrName": "\u88e4\u957f", "attrNameId": 20727, "attrVal": "\u4e5d\u5206\u88e4", "goodsId": "2c9257a15dea5b37015dee11ccac001c", "id": 20764}], [{"attrName": "\u8d27\u53f7", "attrNameId": 20728, "attrVal": "SJ20170816-1", "goodsId": "2c9257a15dea5b37015dee11ccac001c", "id": 20765}, {"attrName": "\u5973\u88e4\u88e4\u578b", "attrNameId": 20729, "attrVal": "\u9614\u817f\u88e4", "goodsId": "2c9257a15dea5b37015dee11ccac001c", "id": 20766}], [{"attrName": "\u5973\u88e4\u8170\u9ad8", "attrNameId": 20730, "attrVal": "\u9ad8\u8170", "goodsId": "2c9257a15dea5b37015dee11ccac001c", "id": 20767}, {"attrName": "\u9762\u6599", "attrNameId": 20731, "attrVal": "\u9ebb", "goodsId": "2c9257a15dea5b37015dee11ccac001c", "id": 20768}], [{"attrName": "\u98ce\u683c", "attrNameId": 20732, "attrVal": "\u767e\u642d", "goodsId": "2c9257a15dea5b37015dee11ccac001c", "id": 20769}, {"attrName": "\u989c\u8272\u5206\u7c7b", "attrNameId": 20733, "attrVal": "\u7816\u7ea2\u8272 \u9ed1\u8272", "goodsId": "2c9257a15dea5b37015dee11ccac001c", "id": 20770}], [{"attrName": "\u670d\u88c5\u6b3e\u5f0f\u7ec6\u8282", "attrNameId": 20734, "attrVal": "\u7ed1\u5e26", "goodsId": "2c9257a15dea5b37015dee11ccac001c", "id": 20771}, {"attrName": "\u539a\u8584", "attrNameId": 20735, "attrVal": "\u5e38\u89c4", "goodsId": "2c9257a15dea5b37015dee11ccac001c", "id": 20772}], [{"attrName": "\u5e74\u4efd\u5b63\u8282", "attrNameId": 20736, "attrVal": " 2017\u5e74\u79cb\u5b63", "goodsId": "2c9257a15dea5b37015dee11ccac001c", "id": 20773}, {"attrName": "\u5c3a\u5bf8", "attrNameId": 20737, "attrVal": "S M", "goodsId": "2c9257a15dea5b37015dee11ccac001c", "id": 20774}]], "brandName": "\u7d20\u6d01", "businessId": "4028800457b6cf7a0157b7998c39001d", "businessName": "\u5e7f\u5dde\u7d20\u6d01\u670d\u9970\u516c\u53f8", "code": "SJ20170816-1", "detailInfo": "<p><img src=\"http://localhost:5000/images/201708171041091596053.jpg\" title=\"201708171041091596053.jpg\"/></p><p><img src=\"http://localhost:5000/images/201708171041095277053.jpg\" title=\"201708171041095277053.jpg\"/></p><p><img src=\"http://localhost:5000/images/201708171041095623070.jpg\" title=\"201708171041095623070.jpg\"/></p><p><img src=\"http://localhost:5000/images/201708171041092204513.jpg\" title=\"201708171041092204513.jpg\"/></p><p><img src=\"http://localhost:5000/images/201708171041123217998.jpg\" title=\"201708171041123217998.jpg\"/></p><p><img src=\"http://localhost:5000/images/201708171041119171231.jpg\" title=\"201708171041119171231.jpg\"/></p><p><img src=\"http://localhost:5000/images/201708171041147957777.jpg\" title=\"201708171041147957777.jpg\"/></p><p><img src=\"http://localhost:5000/images/201708171041149656741.jpg\" title=\"201708171041149656741.jpg\"/></p><p><img src=\"http://localhost:5000/images/201708171041126792045.jpg\" title=\"201708171041126792045.jpg\"/></p><p><img src=\"http://localhost:5000/images/201708171041172409310.jpg\" title=\"201708171041172409310.jpg\"/></p><p><img src=\"http://localhost:5000/images/201708171041207787854.jpg\" title=\"201708171041207787854.jpg\"/></p><p><img src=\"http://localhost:5000/images/201708171041180490143.jpg\" title=\"201708171041180490143.jpg\"/></p><p><img src=\"http://localhost:5000/images/201708171041222881908.jpg\" title=\"201708171041222881908.jpg\"/></p><p><img src=\"http://localhost:5000/images/201708171041242321647.jpg\" title=\"201708171041242321647.jpg\"/></p><p><img src=\"http://localhost:5000/images/201708171041269693660.jpg\" title=\"201708171041269693660.jpg\"/></p><p><img src=\"http://localhost:5000/images/201708171041282713377.jpg\" title=\"201708171041282713377.jpg\"/></p><p><img src=\"http://localhost:5000/images/201708171041300465252.jpg\" title=\"201708171041300465252.jpg\"/></p><p><img src=\"http://localhost:5000/images/201708171041327127491.jpg\" title=\"201708171041327127491.jpg\"/></p><p><img src=\"http://localhost:5000/images/201708171041328682670.jpg\" title=\"201708171041328682670.jpg\"/></p><p><img src=\"http://localhost:5000/images/201708171041358114413.jpg\" title=\"201708171041358114413.jpg\"/></p><p><img src=\"http://localhost:5000/images/201708171041374073596.jpg\" title=\"201708171041374073596.jpg\"/></p><p><img src=\"http://localhost:5000/images/201708171041404600492.jpg\" title=\"201708171041404600492.jpg\"/></p><p><img src=\"http://localhost:5000/images/201708171041395090221.jpg\" title=\"201708171041395090221.jpg\"/></p><p><img src=\"http://localhost:5000/images/201708171041428263039.jpg\" title=\"201708171041428263039.jpg\"/></p><p><img src=\"http://localhost:5000/images/201708171041448615470.jpg\" title=\"201708171041448615470.jpg\"/></p><p><img src=\"http://localhost:5000/images/201708171041441635200.jpg\" title=\"201708171041441635200.jpg\"/></p><p><br/></p>", "evaluateCount": 0, "freeShipNum": 5, "freight": 0, "goodsSkuId": "2c9257a15dea5b37015dee11ccc90022", "goodsSkuList": [{"goodsCode": "SJ20170816-1", "goodsId": "2c9257a15dea5b37015dee11ccac001c", "id": "2c9257a15dea5b37015dee11ccc90022", "price": 59, "saleCount": 10, "skuNameIds": "[696,697]", "skuNames": "[\"\u5c3a\u7801\",\"\u989c\u8272\"]", "skuValIds": "[1715,1717]", "skuVals": "[\"S\",\"\u7816\u7ea2\u8272\"]", "stockNum": 490, "stockNumWarn": 0}, {"goodsCode": "SJ20170816-1", "goodsId": "2c9257a15dea5b37015dee11ccac001c", "id": "2c9257a15dea5b37015dee11ccd70023", "price": 59, "saleCount": 0, "skuNameIds": "[696,697]", "skuNames": "[\"\u5c3a\u7801\",\"\u989c\u8272\"]", "skuValIds": "[1715,1718]", "skuVals": "[\"S\",\"\u9ed1\u8272\"]", "stockNum": 500, "stockNumWarn": 0}, {"goodsCode": "SJ20170816-1", "goodsId": "2c9257a15dea5b37015dee11ccac001c", "id": "2c9257a15dea5b37015dee11ccd90024", "price": 59, "saleCount": 0, "skuNameIds": "[696,697]", "skuNames": "[\"\u5c3a\u7801\",\"\u989c\u8272\"]", "skuValIds": "[1716,1717]", "skuVals": "[\"M\",\"\u7816\u7ea2\u8272\"]", "stockNum": 500, "stockNumWarn": 0}, {"goodsCode": "SJ20170816-1", "goodsId": "2c9257a15dea5b37015dee11ccac001c", "id": "2c9257a15dea5b37015dee11ccdb0025", "price": 59, "saleCount": 0, "skuNameIds": "[696,697]", "skuNames": "[\"\u5c3a\u7801\",\"\u989c\u8272\"]", "skuValIds": "[1716,1718]", "skuVals": "[\"M\",\"\u9ed1\u8272\"]", "stockNum": 500, "stockNumWarn": 0}], "goodsSkuNameList": [{"skuName": "\u5c3a\u7801", "skuValList": [{"current": true, "skuVal": "S", "skuNameId": 696, "skuValId": 1715}, {"current": false, "skuVal": "M", "skuNameId": 696, "skuValId": 1716}], "skuNameId": 696}, {"skuName": "\u989c\u8272", "skuValList": [{"current": true, "skuVal": "\u7816\u7ea2\u8272", "skuNameId": 697, "skuValId": 1717}, {"current": false, "skuVal": "\u9ed1\u8272", "skuNameId": 697, "skuValId": 1718}], "skuNameId": 697}], "goodsSkuValIds": [1715, 1717], "goodsSkuVals": ["S", "\u7816\u7ea2\u8272"], "id": "2c9257a15dea5b37015dee11ccac001c", "logo": "http://localhost:5000/images/201708171037235861039.jpg", "marketPrice": 118, "minBuyNum": 3, "name": "\u97e9\u7248\u5bbd\u677e\u6536\u8170\u7cfb\u5e26\u8377\u53f6\u8fb9\u767e\u642d\u9ad8\u8170\u4e5d\u5206\u88e4 SJ20170816-1", "photoList": [{"goodsId": "2c9257a15dea5b37015dee11ccac001c", "id": "2c9257a160a304ce0160a67a6a080499", "photo": "http://localhost:5000/images/201708171037235861039.jpg", "thumPhoto": "http://localhost:5000/images/201708171037235861039_thumbnail.jpg"}, {"goodsId": "2c9257a15dea5b37015dee11ccac001c", "id": "2c9257a160a304ce0160a67a6a0a049a", "photo": "http://localhost:5000/images/201708171037287594456.jpg", "thumPhoto": "http://localhost:5000/images/201708171037287594456_thumbnail.jpg"}, {"goodsId": "2c9257a15dea5b37015dee11ccac001c", "id": "2c9257a160a304ce0160a67a6a0b049b", "photo": "http://localhost:5000/images/201708171037329295768.jpg", "thumPhoto": "http://localhost:5000/images/201708171037329295768_thumbnail.jpg"}, {"goodsId": "2c9257a15dea5b37015dee11ccac001c", "id": "2c9257a160a304ce0160a67a6a0d049c", "photo": "http://localhost:5000/images/201708171037374436344.jpg", "thumPhoto": "http://localhost:5000/images/201708171037374436344_thumbnail.jpg"}, {"goodsId": "2c9257a15dea5b37015dee11ccac001c", "id": "2c9257a160a304ce0160a67a6a0e049d", "photo": "http://localhost:5000/images/201708171037396158720.jpg", "thumPhoto": "http://localhost:5000/images/201708171037396158720_thumbnail.jpg"}], "price": 59, "saleCount": 10, "shareAmount": null, "shareTimes": null, "shareTips": null, "sourceFlag": 1, "startTime": "2017-08-17 10:42:10", "status": 1, "stockNum": 490, "thumLogo": "http://localhost:5000/images/201708171037235861039_thumbnail.jpg", "validEndTime": "2017-09-20 23:55:50", "wholeNum": 3, "wholePrice": 54}, "validDate": 0}