{"msg": "", "code": "0", "data": {"attrList": [], "brandName": "\u7d20\u6d01", "businessId": "4028800457b6cf7a0157b7998c39001d", "businessName": "\u5e7f\u5dde\u7d20\u6d01\u670d\u9970\u516c\u53f8", "code": "t18c0108", "detailInfo": "<p><img src=\"http://localhost:5000/images/201803241021297361834.jpg\" title=\"201803241021297361834.jpg\"/><br/></p><p><img src=\"http://localhost:5000/images/201803241021297525941.jpg\" title=\"201803241021297525941.jpg\"/></p><p><img src=\"http://localhost:5000/images/201803241021297620055.jpg\" title=\"201803241021297620055.jpg\"/></p><p><img src=\"http://localhost:5000/images/201803241021298099101.jpg\" title=\"201803241021298099101.jpg\"/></p><p><img src=\"http://localhost:5000/images/201803241021298861070.jpg\" title=\"201803241021298861070.jpg\"/></p><p><img src=\"http://localhost:5000/images/201803241021299410711.jpg\" title=\"201803241021299410711.jpg\"/></p><p><img src=\"http://localhost:5000/images/201803241021300100490.jpg\" title=\"201803241021300100490.jpg\"/></p><p><img src=\"http://localhost:5000/images/201803241021300724004.jpg\" title=\"201803241021300724004.jpg\"/></p><p><img src=\"http://localhost:5000/images/201803241021301389871.jpg\" title=\"201803241021301389871.jpg\"/></p><p><img src=\"http://localhost:5000/images/201803241021308801490.jpg\" title=\"201803241021308801490.jpg\"/></p><p><img src=\"http://localhost:5000/images/201803241021316546160.jpg\" title=\"201803241021316546160.jpg\"/></p><p><img src=\"http://localhost:5000/images/201803241021312705806.jpg\" title=\"201803241021312705806.jpg\"/></p><p><img src=\"http://localhost:5000/images/201803241021323775254.jpg\" title=\"201803241021323775254.jpg\"/></p><p><br/></p>", "evaluateCount": 0, "freeShipNum": 0, "freight": 0, "goodsSkuId": "2c9257a16136c3d6016255d012063083", "goodsSkuList": [{"goodsCode": "t18c0108", "goodsId": "2c9257a16136c3d6016255d011e8307d", "id": "2c9257a16136c3d6016255d012063083", "price": 106, "saleCount": 0, "skuNameIds": "[1402,1403]", "skuNames": "[\"\u5c3a\u7801\",\"\u989c\u8272\"]", "skuValIds": "[3461,3464]", "skuVals": "[\"S\",\"\u9ed1\u8272\"]", "stockNum": 100, "stockNumWarn": 0}, {"goodsCode": "t18c0108", "goodsId": "2c9257a16136c3d6016255d011e8307d", "id": "2c9257a16136c3d6016255d012093084", "price": 106, "saleCount": 0, "skuNameIds": "[1402,1403]", "skuNames": "[\"\u5c3a\u7801\",\"\u989c\u8272\"]", "skuValIds": "[3461,3465]", "skuVals": "[\"S\",\"\u5361\u5176\u8272\"]", "stockNum": 100, "stockNumWarn": 0}, {"goodsCode": "t18c0108", "goodsId": "2c9257a16136c3d6016255d011e8307d", "id": "2c9257a16136c3d6016255d0120b3085", "price": 106, "saleCount": 0, "skuNameIds": "[1402,1403]", "skuNames": "[\"\u5c3a\u7801\",\"\u989c\u8272\"]", "skuValIds": "[3462,3464]", "skuVals": "[\"M\",\"\u9ed1\u8272\"]", "stockNum": 100, "stockNumWarn": 0}, {"goodsCode": "t18c0108", "goodsId": "2c9257a16136c3d6016255d011e8307d", "id": "2c9257a16136c3d6016255d0120d3086", "price": 106, "saleCount": 0, "skuNameIds": "[1402,1403]", "skuNames": "[\"\u5c3a\u7801\",\"\u989c\u8272\"]", "skuValIds": "[3462,3465]", "skuVals": "[\"M\",\"\u5361\u5176\u8272\"]", "stockNum": 100, "stockNumWarn": 0}, {"goodsCode": "t18c0108", "goodsId": "2c9257a16136c3d6016255d011e8307d", "id": "2c9257a16136c3d6016255d012103087", "price": 106, "saleCount": 0, "skuNameIds": "[1402,1403]", "skuNames": "[\"\u5c3a\u7801\",\"\u989c\u8272\"]", "skuValIds": "[3463,3464]", "skuVals": "[\"L\",\"\u9ed1\u8272\"]", "stockNum": 100, "stockNumWarn": 0}, {"goodsCode": "t18c0108", "goodsId": "2c9257a16136c3d6016255d011e8307d", "id": "2c9257a16136c3d6016255d012123088", "price": 106, "saleCount": 0, "skuNameIds": "[1402,1403]", "skuNames": "[\"\u5c3a\u7801\",\"\u989c\u8272\"]", "skuValIds": "[3463,3465]", "skuVals": "[\"L\",\"\u5361\u5176\u8272\"]", "stockNum": 100, "stockNumWarn": 0}], "goodsSkuNameList": [{"skuName": "\u5c3a\u7801", "skuValList": [{"current": true, "skuVal": "S", "skuNameId": 1402, "skuValId": 3461}, {"current": false, "skuVal": "M", "skuNameId": 1402, "skuValId": 3462}, {"current": false, "skuVal": "L", "skuNameId": 1402, "skuValId": 3463}], "skuNameId": 1402}, {"skuName": "\u989c\u8272", "skuValList": [{"current": true, "skuVal": "\u9ed1\u8272", "skuNameId": 1403, "skuValId": 3464}, {"current": false, "skuVal": "\u5361\u5176\u8272", "skuNameId": 1403, "skuValId": 3465}], "skuNameId": 1403}], "goodsSkuValIds": [3461, 3464], "goodsSkuVals": ["S", "\u9ed1\u8272"], "id": "2c9257a16136c3d6016255d011e8307d", "logo": "http://localhost:5000/images/201803241019408187009.jpg", "marketPrice": 199, "minBuyNum": 3, "name": "2018\u6625\u590f\u65f6\u5c1a\u65b0\u6b3e\u4f18\u96c5\u4e0a\u8863t18c0108", "photoList": [{"goodsId": "2c9257a16136c3d6016255d011e8307d", "id": "2c9257a16136c3d6016255d011eb307e", "photo": "http://localhost:5000/images/201803241019408187009.jpg", "thumPhoto": "http://localhost:5000/images/201803241019408187009_thumbnail.jpg"}, {"goodsId": "2c9257a16136c3d6016255d011e8307d", "id": "2c9257a16136c3d6016255d011ed307f", "photo": "http://localhost:5000/images/201803241019495030693.jpg", "thumPhoto": "http://localhost:5000/images/201803241019495030693_thumbnail.jpg"}, {"goodsId": "2c9257a16136c3d6016255d011e8307d", "id": "2c9257a16136c3d6016255d011f03080", "photo": "http://localhost:5000/images/201803241019515324126.jpg", "thumPhoto": "http://localhost:5000/images/201803241019515324126_thumbnail.jpg"}, {"goodsId": "2c9257a16136c3d6016255d011e8307d", "id": "2c9257a16136c3d6016255d011f23081", "photo": "http://localhost:5000/images/201803241019537832293.jpg", "thumPhoto": "http://localhost:5000/images/201803241019537832293_thumbnail.jpg"}, {"goodsId": "2c9257a16136c3d6016255d011e8307d", "id": "2c9257a16136c3d6016255d011f43082", "photo": "http://localhost:5000/images/201803241019553707721.jpg", "thumPhoto": "http://localhost:5000/images/201803241019553707721_thumbnail.jpg"}], "price": 106, "saleCount": 76, "shareAmount": 3, "shareTimes": 5, "shareTips": "\u6b64\u5546\u54c1\u5206\u4eab5\u4e2a\u597d\u53cb\uff0c\u4ed8\u6b3e\u7acb\u51cf3\u5143\uff01", "sourceFlag": 1, "startTime": "2018-03-24 10:22:02", "status": 1, "stockNum": 100, "thumLogo": "http://localhost:5000/images/201803241019408187009_thumbnail.jpg", "validEndTime": "2020-03-24 10:08:58", "wholeNum": 3, "wholePrice": 101}, "validDate": 1}